command_creator/__init__.py
command_creator/_info.py
command_creator/py.typed
command_creator-2.3.1.dist-info/licenses/LICENSE
command_creator-2.3.1.dist-info/METADATA
command_creator-2.3.1.dist-info/WHEEL
command_creator-2.3.1.dist-info/top_level.txt
command_creator-2.3.1.dist-info/RECORD
